requests_anon/__init__.py
requests_anon-0.1.1.dist-info/LICENSE
requests_anon-0.1.1.dist-info/METADATA
requests_anon-0.1.1.dist-info/WHEEL
requests_anon-0.1.1.dist-info/RECORD
