Metadata-Version: 2.1
Name: requests-anon
Version: 0.1.1
Summary: Execute HTTPS requests to a server using anonymous proxies.
Author: Nicolò Boschi
Author-email: boschi1997@gmail.com
Requires-Python: >=3.9,<4.0
Classifier: Programming Language :: Python :: 3
Classifier: Programming Language :: Python :: 3.9
Classifier: Programming Language :: Python :: 3.10
Classifier: Programming Language :: Python :: 3.11
Classifier: Programming Language :: Python :: 3.12
Requires-Dist: requests[socks] (>=2.32.3,<3.0.0)
